flake8_disrespectful_code.py
flake8_disrespectful_code-0.0.1.dist-info/DESCRIPTION.rst
flake8_disrespectful_code-0.0.1.dist-info/METADATA
flake8_disrespectful_code-0.0.1.dist-info/RECORD
flake8_disrespectful_code-0.0.1.dist-info/WHEEL
flake8_disrespectful_code-0.0.1.dist-info/entry_points.txt
flake8_disrespectful_code-0.0.1.dist-info/metadata.json
flake8_disrespectful_code-0.0.1.dist-info/top_level.txt
