Metadata-Version: 2.0
Name: flake8-disrespectful-code
Version: 0.0.1
Summary: My example Flake8 extension
Home-page: https://github.com/jargnar/flake8-disrespectful-code
Author: Suhas
Author-email: jargnar@gmail.com
License: MIT
Download-URL: https://github.com/jargnar/flake8-disrespectful-code/archive/0.0.1.tar.gz
Platform: UNKNOWN
Classifier: Framework :: Flake8
Classifier: Environment :: Console
Classifier: Intended Audience :: Developers
Classifier: License :: OSI Approved :: MIT License
Classifier: Programming Language :: Python
Classifier: Programming Language :: Python :: 2
Classifier: Programming Language :: Python :: 3
Classifier: Topic :: Software Development :: Libraries :: Python Modules
Classifier: Topic :: Software Development :: Quality Assurance
Requires-Dist: flake8 (>3.0.0)
